infra_cli/__init__.py
infra_cli/__main__.py
infra_cli/cli.py
infra_cli/api/__init__.py
infra_cli/api/api.py
infra_cli/api/base.py
infra_cli/api/types.py
infra_cli/api/testing/__init__.py
infra_cli/api/testing/fake_api.py
infra_cli/commands/__init__.py
infra_cli/commands/base.py
infra_cli/commands/drift.py
infra_cli/commands/drift_test.py
infra_cli/github/__init__.py
infra_cli/github/base.py
infra_cli/github/service.py
infra_cli/terraform/__init__.py
infra_cli/terraform/base.py
infra_cli/terraform/command_runner.py
infra_cli/terraform/testing/__init__.py
infra_cli/terraform/testing/fake_command_runner.py
infra_new-0.1.0.dev22.dist-info/METADATA
infra_new-0.1.0.dev22.dist-info/WHEEL
infra_new-0.1.0.dev22.dist-info/entry_points.txt
infra_new-0.1.0.dev22.dist-info/top_level.txt
infra_new-0.1.0.dev22.dist-info/RECORD
