Metadata-Version: 2.4
Name: infra-new
Version: 0.1.0.dev22
Summary: Add your description here
Requires-Python: >=3.11
Requires-Dist: aiohttp[speedups]>=3.12.14
Requires-Dist: asyncer>=0.0.8
Requires-Dist: python-dotenv>=1.1.1
Requires-Dist: typer>=0.16.0
